{"features": [{"geometry": {"coordinates": [-6.3537145, 32.328858], "type": "Point"}, "id": 2068353391, "properties": {"amenity": "hospital", "emergency": "no"}, "type": "Feature"}, {"geometry": {"coordinates": [-6.3602737, 32.3336887], "type": "Point"}, "id": 4230313822, "properties": {"addr:city": "B\u00e9ni Mellal", "addr:postcode": "23000", "addr:street": "Avenue Mohammed V, 1 \u00e8re \u00e9tage", "amenity": "hospital", "name": "Laboratoire Central D'Analyses M\u00e9dicales du Tadla", "phone": "0523486448"}, "type": "Feature"}], "type": "FeatureCollection"}